makemake90.py
makemake90-0.4.dist-info/entry_points.txt
makemake90-0.4.dist-info/licenses/LICENSE
makemake90-0.4.dist-info/WHEEL
makemake90-0.4.dist-info/METADATA
makemake90-0.4.dist-info/RECORD
