Metadata-Version: 2.4
Name: makemake90
Version: 0.4
Summary: Generate Makefiles for modular Fortran programs
Author: Jan Berges
Requires-Python: >=2.7
Classifier: License :: OSI Approved :: Zero-Clause BSD (0BSD)
Classifier: Programming Language :: Python
License-File: LICENSE
Project-URL: Homepage, https://github.com/janberges/makemake90
